{"key":"content:fr:docs:5.configuration-glossary:26.configuration-runtime-config.md","generatedAt":"2022-03-15T12:18:24.993Z","mtime":"2022-03-15T12:18:24.990Z","slug":"configuration-runtime-config","title":"Propriétés RuntimeConfig","position":"999900050026","to":"/docs/configuration-glossary/configuration-runtime-config","draft":false,"page":true,"language":"fr","navigation":{"title":"RuntimeConfig"},"description":"RuntimeConfig permet de passer des variables d'environnement et de la configuration dynamique au contexte de Nuxt.","menu":"runtimeConfig","category":"configuration-glossary","empty":false,"body":{"raw":"---\ntitle: Propriétés RuntimeConfig\nnavigation.title: RuntimeConfig\ndescription: RuntimeConfig permet de passer des variables d'environnement et de la configuration dynamique au contexte de Nuxt.\nmenu: runtimeConfig\ncategory: configuration-glossary\n---\n# Propriétés RuntimeConfig\n\nRuntimeConfig permet de passer des variables d'environnement et de la configuration dynamique au contexte de Nuxt. Pour plus d'informations sur l'utilisation, se référer au guide du [runtime config](/docs/configuration-glossary/configuration-runtime-config).\n\n---\n## `publicRuntimeConfig`\n\n- Type: `Object`\n\nLa valeur de cet objet est **accessible du côté client et du côté serveur** en utilisant `$config`.\n\n## `privateRuntimeConfig`\n\n- Type: `Object`\n\nLa valeur de cet objet est accessible du **côté serveur seulement** en utilisant `$config`. Cela écrase `publicRuntimeConfig` pour le serveur.\n","ast":{"type":"root","children":[{"type":"element","tag":"prose-h1","props":{"class":"d-heading-title","id":"propriétés-runtimeconfig"},"children":[{"type":"text","value":"Propriétés RuntimeConfig"}]},{"type":"text","value":"\n"},{"type":"element","tag":"prose-paragraph","props":{"class":"d-heading-description"},"children":[{"type":"text","value":"RuntimeConfig permet de passer des variables d'environnement et de la configuration dynamique au contexte de Nuxt. Pour plus d'informations sur l'utilisation, se référer au guide du "},{"type":"element","tag":"prose-a","props":{"href":"/docs/configuration-glossary/configuration-runtime-config"},"children":[{"type":"text","value":"runtime config"}]},{"type":"text","value":"."}]},{"type":"text","value":"\n"},{"type":"element","tag":"prose-hr","props":{"class":"d-heading-hr"},"children":[]},{"type":"text","value":"\n"},{"type":"element","tag":"prose-h2","props":{"id":"publicruntimeconfig"},"children":[{"type":"element","tag":"prose-a","props":{"href":"#publicruntimeconfig"},"children":[{"type":"element","tag":"prose-code-inline","props":{},"children":[{"type":"text","value":"publicRuntimeConfig"}]}]}]},{"type":"text","value":"\n"},{"type":"element","tag":"prose-ul","props":{},"children":[{"type":"text","value":"\n"},{"type":"element","tag":"prose-li","props":{},"children":[{"type":"text","value":"\n"},{"type":"text","value":"Type: "},{"type":"element","tag":"prose-code-inline","props":{},"children":[{"type":"text","value":"Object"}]},{"type":"text","value":"\n"}]},{"type":"text","value":"\n"}]},{"type":"text","value":"\n"},{"type":"element","tag":"prose-paragraph","props":{},"children":[{"type":"text","value":"La valeur de cet objet est "},{"type":"element","tag":"prose-strong","props":{},"children":[{"type":"text","value":"accessible du côté client et du côté serveur"}]},{"type":"text","value":" en utilisant "},{"type":"element","tag":"prose-code-inline","props":{},"children":[{"type":"text","value":"$config"}]},{"type":"text","value":"."}]},{"type":"text","value":"\n"},{"type":"element","tag":"prose-h2","props":{"id":"privateruntimeconfig"},"children":[{"type":"element","tag":"prose-a","props":{"href":"#privateruntimeconfig"},"children":[{"type":"element","tag":"prose-code-inline","props":{},"children":[{"type":"text","value":"privateRuntimeConfig"}]}]}]},{"type":"text","value":"\n"},{"type":"element","tag":"prose-ul","props":{},"children":[{"type":"text","value":"\n"},{"type":"element","tag":"prose-li","props":{},"children":[{"type":"text","value":"\n"},{"type":"text","value":"Type: "},{"type":"element","tag":"prose-code-inline","props":{},"children":[{"type":"text","value":"Object"}]},{"type":"text","value":"\n"}]},{"type":"text","value":"\n"}]},{"type":"text","value":"\n"},{"type":"element","tag":"prose-paragraph","props":{},"children":[{"type":"text","value":"La valeur de cet objet est accessible du "},{"type":"element","tag":"prose-strong","props":{},"children":[{"type":"text","value":"côté serveur seulement"}]},{"type":"text","value":" en utilisant "},{"type":"element","tag":"prose-code-inline","props":{},"children":[{"type":"text","value":"$config"}]},{"type":"text","value":". Cela écrase "},{"type":"element","tag":"prose-code-inline","props":{},"children":[{"type":"text","value":"publicRuntimeConfig"}]},{"type":"text","value":" pour le serveur."}]}]},"toc":{"title":"","searchDepth":2,"depth":2,"links":[{"id":"publicruntimeconfig","depth":2,"text":"publicRuntimeConfig"},{"id":"privateruntimeconfig","depth":2,"text":"privateRuntimeConfig"}]}}}